BotBooster/__init__.py
BotBooster-0.0.3.dist-info/LICENSE
BotBooster-0.0.3.dist-info/METADATA
BotBooster-0.0.3.dist-info/WHEEL
BotBooster-0.0.3.dist-info/entry_points.txt
BotBooster-0.0.3.dist-info/top_level.txt
BotBooster-0.0.3.dist-info/RECORD
