Metadata-Version: 2.1
Name: BotBooster
Version: 0.0.3
Summary: for replit bots
Home-page: https://tiktok.com/@noteason
Author: noteason
Author-email: tiktoknoteason@gmail.com
License: MIT
Platform: UNKNOWN
Classifier: License :: OSI Approved :: MIT License
Classifier: Programming Language :: Python :: 3
Classifier: Programming Language :: Python :: 3.7
Requires-Dist: requests
